cvhough_sdk/__init__.py
cvhough_sdk/main.py
cvhough_sdk/models/best1.pt
circle_cvhough-1.0.0.dist-info/METADATA
circle_cvhough-1.0.0.dist-info/WHEEL
circle_cvhough-1.0.0.dist-info/entry_points.txt
circle_cvhough-1.0.0.dist-info/top_level.txt
circle_cvhough-1.0.0.dist-info/RECORD
